gryannote_audio/__init__.py
gryannote_audio/audio_labeling.py
gryannote_audio/audio_labeling.pyi
gryannote_audio/core.py
gryannote_audio/templates/component/__vite-browser-external-DYxpcVy9.js
gryannote_audio/templates/component/index.js
gryannote_audio/templates/component/module-BPgIyIuo.js
gryannote_audio/templates/component/module-DwKaDiT1.js
gryannote_audio/templates/component/module-wPUp6Scx.js
gryannote_audio/templates/component/style.css
gryannote_audio/templates/component/wrapper-6f348d45-B5bCGhfq.js
gryannote_audio/templates/example/index.js
gryannote_audio/templates/example/style.css
gryannote_pipeline/__init__.py
gryannote_pipeline/pipelineselector.py
gryannote_pipeline/pipelineselector.pyi
gryannote_pipeline/templates/component/index.js
gryannote_pipeline/templates/component/style.css
gryannote_pipeline/templates/example/index.js
gryannote_pipeline/templates/example/style.css
gryannote_rttm/__init__.py
gryannote_rttm/rttm.py
gryannote_rttm/rttm.pyi
gryannote_rttm/templates/component/__vite-browser-external-DYxpcVy9.js
gryannote_rttm/templates/component/index.js
gryannote_rttm/templates/component/style.css
gryannote_rttm/templates/component/wrapper-6f348d45-B5bCGhfq.js
gryannote_rttm/templates/example/index.js
gryannote_rttm/templates/example/style.css
gryannote-0.3.3.dist-info/METADATA
gryannote-0.3.3.dist-info/WHEEL
gryannote-0.3.3.dist-info/licenses/LICENSE
gryannote-0.3.3.dist-info/RECORD
