Metadata-Version: 2.3
Name: gryannote
Version: 0.3.3
Summary: Provide Gradio custom components to make the diarization-based audio annotation process easier
Project-URL: Homepage, https://github.com/clement-pages/gryannote
Author-email: Clément Pagés <clement.pages@irit.fr>
License: MIT License
License-File: LICENSE
Keywords: annotation-tool,audio,gradio-custom-component,pyannote,speaker-diarization
Classifier: Development Status :: 3 - Alpha
Classifier: License :: OSI Approved :: MIT License
Classifier: Operating System :: OS Independent
Classifier: Programming Language :: Python :: 3
Classifier: Programming Language :: Python :: 3 :: Only
Classifier: Programming Language :: Python :: 3.10
Classifier: Programming Language :: Python :: 3.11
Classifier: Topic :: Scientific/Engineering
Classifier: Topic :: Scientific/Engineering :: Artificial Intelligence
Classifier: Topic :: Scientific/Engineering :: Visualization
Requires-Python: >=3.10
Requires-Dist: fastapi==0.112.4
Requires-Dist: gradio==4.27.0
Requires-Dist: pyannote-audio>=3.1.1
Requires-Dist: pyannote-core>=5.0.0
Provides-Extra: dev
Requires-Dist: build; extra == 'dev'
Requires-Dist: twine; extra == 'dev'
